pbs_tui/__init__.py
pbs_tui/__main__.py
pbs_tui/app.py
pbs_tui/app.tcss
pbs_tui/data.py
pbs_tui/fetcher.py
pbs_tui/nodes.py
pbs_tui/samples.py
pbs_tui/ui_config.py
pbs_tui-0.4.0.dist-info/WHEEL
pbs_tui-0.4.0.dist-info/entry_points.txt
pbs_tui-0.4.0.dist-info/METADATA
pbs_tui-0.4.0.dist-info/RECORD
