Metadata-Version: 2.3
Name: pbs-tui
Version: 0.4.0
Summary: Textual TUI dashboard for monitoring PBS Pro schedulers
Author: Sam Foreman, Argonne Leadership Computing Facility
Author-email: Sam Foreman <foremans@anl.gov>
Requires-Dist: textual
Requires-Dist: pytest>=8.4.2 ; extra == 'dev'
Requires-Python: >=3.10
Provides-Extra: dev
